setup.py
census_places/__init__.py
census_places/admin.py
census_places/enums.py
census_places/models.py
census_places/management/__init__.py
census_places/management/commands/__init__.py
census_places/management/commands/import_places.py
census_places/migrations/0001_initial.py
census_places/migrations/0002_auto__add_zipboundary.py
census_places/migrations/__init__.py
django_census_places.egg-info/PKG-INFO
django_census_places.egg-info/SOURCES.txt
django_census_places.egg-info/dependency_links.txt
django_census_places.egg-info/top_level.txt