Metadata-Version: 1.1
Name: django-census-places
Version: 1.2.4
Summary: Use city (and census designated place) and ZIP Code boundaries provided by the United States Census
Home-page: http://bitbucket.org/latestrevision/django-census-places/
Author: Adam Coddington
Author-email: me@adamcoddington.net
License: UNKNOWN
Platform: UNKNOWN
Classifier: Framework :: Django
Classifier: Intended Audience :: Developers
Classifier: License :: OSI Approved :: MIT License
Classifier: Operating System :: OS Independent
Classifier: Programming Language :: Python
Classifier: Topic :: Scientific/Engineering :: GIS
